<?xml version="1.0" encoding="UTF-8"?>
<objects serializationModel="Studio.02.02.00">
	<object class="AudioFile" id="{4649e2eb-a3d0-4fa5-be7a-703b36ef0e76}">
		<property name="assetPath">
			<value>01 Rain urban_gentle 1_MS STEREO.WAV</value>
		</property>
		<property name="isStreaming">
			<value>true</value>
		</property>
		<property name="frequencyInKHz">
			<value>96</value>
		</property>
		<property name="channelCount">
			<value>2</value>
		</property>
		<property name="length">
			<value>146.09006249999999</value>
		</property>
		<relationship name="masterAssetFolder">
			<destination>{7b3f5b74-9b34-4aad-9bf1-172249a21b6c}</destination>
		</relationship>
	</object>
</objects>
